fuzzytest/__init__.py
fuzzytest/fuzzytest.py
fuzzytest-0.0.5.dist-info/METADATA
fuzzytest-0.0.5.dist-info/WHEEL
fuzzytest-0.0.5.dist-info/top_level.txt
fuzzytest-0.0.5.dist-info/RECORD
